gradio_praisonai/__init__.py
gradio_praisonai/client.py
gradio_praisonai/interface.py
gradio_praisonai-0.1.0.dist-info/licenses/LICENSE
gradio_praisonai-0.1.0.dist-info/METADATA
gradio_praisonai-0.1.0.dist-info/WHEEL
gradio_praisonai-0.1.0.dist-info/top_level.txt
gradio_praisonai-0.1.0.dist-info/RECORD
